{"type": "linear", "layer": {"conv_in": 26, "conv_out": 857}, "block": [{"type": "normal", "c1": 37, "k": 5, "c2": 19, "s": 1}, {"type": "reduction", "c1": 177, "k": 5, "c2": 31, "s": 2}, {"type": "skip", "c1": 136, "k": 5, "c2": 31, "s": 1}, {"type": "skip", "c1": 104, "k": 3, "c2": 31, "s": 1}, {"type": "reduction", "c1": 167, "k": 5, "c2": 64, "s": 2}, {"type": "skip", "c1": 250, "k": 3, "c2": 64, "s": 1}, {"type": "skip", "c1": 308, "k": 5, "c2": 64, "s": 1}, {"type": "reduction", "c1": 269, "k": 5, "c2": 92, "s": 2}, {"type": "skip", "c1": 146, "k": 3, "c2": 92, "s": 1}, {"type": "skip", "c1": 130, "k": 3, "c2": 92, "s": 1}, {"type": "normal", "c1": 233, "k": 3, "c2": 91, "s": 1}, {"type": "skip", "c1": 70, "k": 3, "c2": 91, "s": 1}, {"type": "skip", "c1": 65, "k": 3, "c2": 91, "s": 1}, {"type": "skip", "c1": 73, "k": 3, "c2": 91, "s": 1}, {"type": "normal", "c1": 242, "k": 3, "c2": 173, "s": 1}, {"type": "skip", "c1": 111, "k": 3, "c2": 173, "s": 1}, {"type": "skip", "c1": 114, "k": 3, "c2": 173, "s": 1}, {"type": "skip", "c1": 118, "k": 3, "c2": 173, "s": 1}]}