{"type": "linear", "layer": {"conv_in": 23, "conv_out": 825}, "block": [{"type": "normal", "c1": 63, "k": 3, "c2": 31, "s": 1}, {"type": "reduction", "c1": 137, "k": 5, "c2": 29, "s": 2}, {"type": "skip", "c1": 19, "k": 5, "c2": 29, "s": 1}, {"type": "skip", "c1": 47, "k": 5, "c2": 29, "s": 1}, {"type": "reduction", "c1": 149, "k": 5, "c2": 49, "s": 2}, {"type": "skip", "c1": 94, "k": 7, "c2": 49, "s": 1}, {"type": "skip", "c1": 68, "k": 3, "c2": 49, "s": 1}, {"type": "reduction", "c1": 172, "k": 5, "c2": 60, "s": 2}, {"type": "skip", "c1": 1, "k": 3, "c2": 60, "s": 1}, {"type": "skip", "c1": 1, "k": 3, "c2": 60, "s": 1}, {"type": "normal", "c1": 264, "k": 3, "c2": 89, "s": 1}, {"type": "skip", "c1": 1, "k": 3, "c2": 89, "s": 1}, {"type": "skip", "c1": 1, "k": 3, "c2": 89, "s": 1}, {"type": "skip", "c1": 1, "k": 3, "c2": 89, "s": 1}, {"type": "normal", "c1": 375, "k": 3, "c2": 218, "s": 1}, {"type": "skip", "c1": 289, "k": 7, "c2": 218, "s": 1}, {"type": "skip", "c1": 73, "k": 7, "c2": 218, "s": 1}, {"type": "skip", "c1": 1, "k": 3, "c2": 218, "s": 1}]}