{"type": "bottleneck", "layer": {"conv_in": 64, "conv_out": 1024}, "block": [{"type": "normal", "c1": 48, "k": 3, "c2": 59, "c3": 159, "s": 1}, {"type": "skip", "c1": 24, "k": 3, "c2": 22, "c3": 159, "s": 1}, {"type": "skip", "c1": 29, "k": 3, "c2": 31, "c3": 159, "s": 1}, {"type": "reduction", "c1": 122, "k": 3, "c2": 118, "c3": 411, "s": 2}, {"type": "skip", "c1": 68, "k": 3, "c2": 98, "c3": 411, "s": 1}, {"type": "skip", "c1": 102, "k": 5, "c2": 99, "c3": 411, "s": 1}, {"type": "skip", "c1": 99, "k": 3, "c2": 102, "c3": 411, "s": 1}, {"type": "reduction", "c1": 232, "k": 3, "c2": 231, "c3": 943, "s": 2}, {"type": "skip", "c1": 177, "k": 5, "c2": 179, "c3": 943, "s": 1}, {"type": "skip", "c1": 168, "k": 5, "c2": 185, "c3": 943, "s": 1}, {"type": "skip", "c1": 156, "k": 5, "c2": 147, "c3": 943, "s": 1}, {"type": "skip", "c1": 216, "k": 5, "c2": 211, "c3": 943, "s": 1}, {"type": "skip", "c1": 200, "k": 3, "c2": 188, "c3": 943, "s": 1}, {"type": "reduction", "c1": 491, "k": 7, "c2": 511, "c3": 1974, "s": 2}, {"type": "skip", "c1": 491, "k": 7, "c2": 498, "c3": 1974, "s": 1}, {"type": "skip", "c1": 476, "k": 5, "c2": 463, "c3": 1974, "s": 1}]}