{"type": "bottleneck", "layer": {"conv_in": 63, "conv_out": 1024}, "block": [{"type": "normal", "c1": 49, "k": 3, "c2": 63, "c3": 229, "s": 1}, {"type": "skip", "c1": 35, "k": 3, "c2": 34, "c3": 229, "s": 1}, {"type": "skip", "c1": 44, "k": 3, "c2": 43, "c3": 229, "s": 1}, {"type": "reduction", "c1": 122, "k": 3, "c2": 118, "c3": 447, "s": 2}, {"type": "skip", "c1": 85, "k": 3, "c2": 108, "c3": 447, "s": 1}, {"type": "skip", "c1": 107, "k": 5, "c2": 107, "c3": 447, "s": 1}, {"type": "skip", "c1": 106, "k": 3, "c2": 110, "c3": 447, "s": 1}, {"type": "reduction", "c1": 234, "k": 3, "c2": 240, "c3": 946, "s": 2}, {"type": "skip", "c1": 224, "k": 5, "c2": 228, "c3": 946, "s": 1}, {"type": "skip", "c1": 203, "k": 5, "c2": 233, "c3": 946, "s": 1}, {"type": "skip", "c1": 208, "k": 5, "c2": 209, "c3": 946, "s": 1}, {"type": "skip", "c1": 225, "k": 5, "c2": 239, "c3": 946, "s": 1}, {"type": "skip", "c1": 215, "k": 3, "c2": 191, "c3": 946, "s": 1}, {"type": "reduction", "c1": 492, "k": 7, "c2": 507, "c3": 1979, "s": 2}, {"type": "skip", "c1": 495, "k": 7, "c2": 498, "c3": 1979, "s": 1}, {"type": "skip", "c1": 482, "k": 7, "c2": 461, "c3": 1979, "s": 1}]}