{"type": "bottleneck", "layer": {"conv_in": 63, "conv_out": 1024}, "block": [{"type": "normal", "c1": 59, "k": 3, "c2": 245, "s": 1}, {"type": "skip", "c1": 58, "k": 3, "c2": 245, "s": 1}, {"type": "skip", "c1": 52, "k": 5, "c2": 245, "s": 1}, {"type": "reduction", "c1": 126, "k": 5, "c2": 483, "s": 2}, {"type": "skip", "c1": 118, "k": 3, "c2": 483, "s": 1}, {"type": "skip", "c1": 107, "k": 3, "c2": 483, "s": 1}, {"type": "skip", "c1": 113, "k": 7, "c2": 483, "s": 1}, {"type": "reduction", "c1": 251, "k": 5, "c2": 1012, "s": 2}, {"type": "skip", "c1": 233, "k": 3, "c2": 1012, "s": 1}, {"type": "skip", "c1": 233, "k": 7, "c2": 1012, "s": 1}, {"type": "skip", "c1": 224, "k": 3, "c2": 1012, "s": 1}, {"type": "skip", "c1": 239, "k": 5, "c2": 1012, "s": 1}, {"type": "skip", "c1": 194, "k": 5, "c2": 1012, "s": 1}, {"type": "reduction", "c1": 477, "k": 7, "c2": 1976, "s": 2}, {"type": "skip", "c1": 424, "k": 3, "c2": 1976, "s": 1}, {"type": "skip", "c1": 508, "k": 7, "c2": 1976, "s": 1}]}