{"type": "bottleneck", "layer": {"conv_in": 63, "conv_out": 1024}, "block": [{"type": "normal", "c1": 62, "k": 5, "c2": 247, "s": 1}, {"type": "skip", "c1": 63, "k": 5, "c2": 247, "s": 1}, {"type": "skip", "c1": 55, "k": 5, "c2": 247, "s": 1}, {"type": "reduction", "c1": 126, "k": 5, "c2": 473, "s": 2}, {"type": "skip", "c1": 126, "k": 3, "c2": 473, "s": 1}, {"type": "skip", "c1": 119, "k": 5, "c2": 473, "s": 1}, {"type": "skip", "c1": 109, "k": 7, "c2": 473, "s": 1}, {"type": "reduction", "c1": 255, "k": 3, "c2": 994, "s": 2}, {"type": "skip", "c1": 246, "k": 7, "c2": 994, "s": 1}, {"type": "skip", "c1": 251, "k": 5, "c2": 994, "s": 1}, {"type": "skip", "c1": 234, "k": 3, "c2": 994, "s": 1}, {"type": "skip", "c1": 242, "k": 5, "c2": 994, "s": 1}, {"type": "skip", "c1": 235, "k": 5, "c2": 994, "s": 1}, {"type": "reduction", "c1": 509, "k": 7, "c2": 2032, "s": 2}, {"type": "skip", "c1": 510, "k": 5, "c2": 2032, "s": 1}, {"type": "skip", "c1": 493, "k": 5, "c2": 2032, "s": 1}]}