{"type": "bottleneck", "layer": {"conv_in": 63, "conv_out": 1023}, "block": [{"type": "normal", "c1": 57, "k": 5, "c2": 237, "s": 1}, {"type": "skip", "c1": 58, "k": 3, "c2": 237, "s": 1}, {"type": "skip", "c1": 60, "k": 3, "c2": 237, "s": 1}, {"type": "reduction", "c1": 120, "k": 3, "c2": 491, "s": 2}, {"type": "skip", "c1": 113, "k": 3, "c2": 491, "s": 1}, {"type": "skip", "c1": 123, "k": 5, "c2": 491, "s": 1}, {"type": "skip", "c1": 116, "k": 3, "c2": 491, "s": 1}, {"type": "reduction", "c1": 252, "k": 3, "c2": 957, "s": 2}, {"type": "skip", "c1": 250, "k": 5, "c2": 957, "s": 1}, {"type": "skip", "c1": 243, "k": 7, "c2": 957, "s": 1}, {"type": "skip", "c1": 236, "k": 5, "c2": 957, "s": 1}, {"type": "skip", "c1": 250, "k": 5, "c2": 957, "s": 1}, {"type": "skip", "c1": 236, "k": 5, "c2": 957, "s": 1}, {"type": "reduction", "c1": 480, "k": 7, "c2": 1652, "s": 2}, {"type": "skip", "c1": 473, "k": 5, "c2": 1652, "s": 1}, {"type": "skip", "c1": 424, "k": 3, "c2": 1652, "s": 1}]}