{"type": "bottleneck", "layer": {"conv_in": 63, "conv_out": 941}, "block": [{"type": "normal", "c1": 50, "k": 5, "c2": 206, "s": 1}, {"type": "skip", "c1": 48, "k": 3, "c2": 206, "s": 1}, {"type": "skip", "c1": 54, "k": 3, "c2": 206, "s": 1}, {"type": "reduction", "c1": 111, "k": 3, "c2": 427, "s": 2}, {"type": "skip", "c1": 96, "k": 3, "c2": 427, "s": 1}, {"type": "skip", "c1": 112, "k": 5, "c2": 427, "s": 1}, {"type": "skip", "c1": 100, "k": 3, "c2": 427, "s": 1}, {"type": "reduction", "c1": 251, "k": 3, "c2": 878, "s": 2}, {"type": "skip", "c1": 231, "k": 5, "c2": 878, "s": 1}, {"type": "skip", "c1": 231, "k": 5, "c2": 878, "s": 1}, {"type": "skip", "c1": 208, "k": 5, "c2": 878, "s": 1}, {"type": "skip", "c1": 234, "k": 5, "c2": 878, "s": 1}, {"type": "skip", "c1": 204, "k": 5, "c2": 878, "s": 1}, {"type": "reduction", "c1": 453, "k": 7, "c2": 1251, "s": 2}, {"type": "skip", "c1": 377, "k": 5, "c2": 1251, "s": 1}, {"type": "skip", "c1": 396, "k": 3, "c2": 1251, "s": 1}]}