{
    "config_type": "nas",
    "b0": {
        "conv_in": 32,
        "stride_in": 1,
        "conv_out": 512
    },
    "block_type": "SoftInvertedResidualBlock",
    "blocks": [
        {
            "e": 3.3444310426712036,
            "c": 31,
            "n": 1,
            "k": 7,
            "s": 1
        },
        {
            "e": 6.176235299196531,
            "c": 30,
            "n": 1,
            "k": 5,
            "s": 2
        },
        {
            "e": 5.433849257532997,
            "c": 32,
            "n": 1,
            "k": 5,
            "s": 1
        },
        {
            "e": 5.967159390449524,
            "c": 32,
            "n": 1,
            "k": 5,
            "s": 1
        },
        {
            "e": 5.939452886581421,
            "c": 64,
            "n": 1,
            "k": 5,
            "s": 2
        },
        {
            "e": 5.535711050033569,
            "c": 64,
            "n": 1,
            "k": 7,
            "s": 1
        },
        {
            "e": 5.409031391143799,
            "c": 64,
            "n": 1,
            "k": 7,
            "s": 1
        },
        {
            "e": 5.055802345275879,
            "c": 91,
            "n": 1,
            "k": 5,
            "s": 2
        },
        {
            "e": 4.6491415390248,
            "c": 90,
            "n": 1,
            "k": 7,
            "s": 1
        },
        {
            "e": 3.7072111091102435,
            "c": 70,
            "n": 1,
            "k": 5,
            "s": 1
        },
        {
            "e": 2.482990209052609,
            "c": 82,
            "n": 1,
            "k": 5,
            "s": 1
        },
        {
            "e": 1.2687522058123055,
            "c": 52,
            "n": 1,
            "k": 3,
            "s": 1
        },
        {
            "e": 1.6679547383073998,
            "c": 48,
            "n": 1,
            "k": 3,
            "s": 1
        },
        {
            "e": 1.5403997059076089,
            "c": 48,
            "n": 1,
            "k": 3,
            "s": 1
        },
        {
            "e": 3.983228752026395,
            "c": 146,
            "n": 1,
            "k": 3,
            "s": 2
        },
        {
            "e": 0.8636046793645701,
            "c": 117,
            "n": 1,
            "k": 3,
            "s": 1
        },
        {
            "e": 1.7299072342155657,
            "c": 158,
            "n": 1,
            "k": 3,
            "s": 1
        },
        {
            "e": 2.2005239719859198,
            "c": 174,
            "n": 1,
            "k": 3,
            "s": 1
        }
    ]
}