{
    "type": "shallow",
    "layer": {
        "conv_in": 62,
        "conv_out": 1022
    },
    "block": [
        {
            "type": "normal",
            "c1": 53,
            "c2": 61,
            "s": 1
        },
        {
            "type": "skip",
            "c1": 50,
            "c2": 61,
            "s": 1
        },
        {
            "type": "reduction",
            "c1": 124,
            "c2": 126,
            "s": 2
        },
        {
            "type": "skip",
            "c1": 116,
            "c2": 126,
            "s": 1
        },
        {
            "type": "reduction",
            "c1": 248,
            "c2": 253,
            "s": 2
        },
        {
            "type": "skip",
            "c1": 246,
            "c2": 253,
            "s": 1
        },
        {
            "type": "reduction",
            "c1": 498,
            "c2": 503,
            "s": 2
        },
        {
            "type": "skip",
            "c1": 488,
            "c2": 503,
            "s": 1
        }
    ]
}